markdown_strikethrough/__init__.py
markdown_strikethrough/extension.py
markdown_strikethrough-0.1.2.dist-info/LICENSE
markdown_strikethrough-0.1.2.dist-info/METADATA
markdown_strikethrough-0.1.2.dist-info/WHEEL
markdown_strikethrough-0.1.2.dist-info/top_level.txt
markdown_strikethrough-0.1.2.dist-info/RECORD
